batchpatcher/__init__.py
batchpatcher/__main__.py
batchpatcher/translate/__init__.py
batchpatcher/translate/deepl_scraper.py
batchpatcher/translate/language_translator.py
batchpatcher-2.2.1.dist-info/LICENSE
batchpatcher-2.2.1.dist-info/METADATA
batchpatcher-2.2.1.dist-info/WHEEL
batchpatcher-2.2.1.dist-info/entry_points.txt
batchpatcher-2.2.1.dist-info/top_level.txt
batchpatcher-2.2.1.dist-info/RECORD
